maskgct/__init__.py
maskgct/version.py
maskgct/codec/__init__.py
maskgct/codec/codec_dataset.py
maskgct/codec/codec_inference.py
maskgct/codec/codec_sampler.py
maskgct/codec/codec_trainer.py
maskgct/codec/facodec/__init__.py
maskgct/codec/facodec/facodec_dataset.py
maskgct/codec/facodec/facodec_inference.py
maskgct/codec/facodec/facodec_trainer.py
maskgct/codec/facodec/optimizer.py
maskgct/codec/facodec/alias_free_torch/__init__.py
maskgct/codec/facodec/alias_free_torch/act.py
maskgct/codec/facodec/alias_free_torch/filter.py
maskgct/codec/facodec/alias_free_torch/resample.py
maskgct/codec/ns3_codec/__init__.py
maskgct/codec/ns3_codec/facodec.py
maskgct/codec/ns3_codec/gradient_reversal.py
maskgct/codec/ns3_codec/melspec.py
maskgct/codec/ns3_codec/transformer.py
maskgct/codec/ns3_codec/alias_free_torch/__init__.py
maskgct/codec/ns3_codec/alias_free_torch/act.py
maskgct/codec/ns3_codec/alias_free_torch/filter.py
maskgct/codec/ns3_codec/alias_free_torch/resample.py
maskgct/codec/ns3_codec/quantize/__init__.py
maskgct/codec/ns3_codec/quantize/fvq.py
maskgct/codec/ns3_codec/quantize/rvq.py
maskgct/tts/__init__.py
maskgct/tts/fastspeech2/__init__.py
maskgct/tts/fastspeech2/fs2.py
maskgct/tts/fastspeech2/fs2_dataset.py
maskgct/tts/fastspeech2/fs2_inference.py
maskgct/tts/fastspeech2/fs2_trainer.py
maskgct/tts/maskgct/__init__.py
maskgct/tts/maskgct/gradio_demo.py
maskgct/tts/maskgct/llama_nar.py
maskgct/tts/maskgct/maskgct_infer_wrapper.py
maskgct/tts/maskgct/maskgct_inference.py
maskgct/tts/maskgct/maskgct_s2a.py
maskgct/tts/maskgct/maskgct_t2s.py
maskgct/tts/maskgct/maskgct_utils.py
maskgct/tts/maskgct/config/maskgct.json
maskgct-0.0.6.dist-info/LICENSE
maskgct-0.0.6.dist-info/METADATA
maskgct-0.0.6.dist-info/WHEEL
maskgct-0.0.6.dist-info/top_level.txt
maskgct-0.0.6.dist-info/RECORD
